fgp/__init__.py
fgp/certification.py
fgp/checkable_models.py
fgp/projections.py
fgp/queues.py
fgp/utils.py
fgp_cert-0.0.3.dist-info/METADATA
fgp_cert-0.0.3.dist-info/WHEEL
fgp_cert-0.0.3.dist-info/top_level.txt
fgp_cert-0.0.3.dist-info/RECORD
