Metadata-Version: 2.1
Name: fgp-cert
Version: 0.0.3
Summary: tool for certifying local robustness in deep networks
Home-page: UNKNOWN
Author: Klas Leino
Author-email: kleino@cs.cmu.edu
License: UNKNOWN
Platform: UNKNOWN
Classifier: Programming Language :: Python :: 3
Classifier: License :: OSI Approved :: MIT License
Requires-Python: >=3.6
Requires-Dist: tensorflow (==1.15)
